tkrcord/__init__.py
tkrcord/__main__.py
tkrcord/cli.py
tkrcord/abc/__init__.py
tkrcord/abc/_activity.py
tkrcord/abc/_bot.py
tkrcord/abc/_channel.py
tkrcord/abc/_client.py
tkrcord/abc/_color.py
tkrcord/abc/_ctx.py
tkrcord/abc/_embed.py
tkrcord/abc/_guild.py
tkrcord/abc/_intents.py
tkrcord/abc/_message.py
tkrcord/abc/_role.py
tkrcord/abc/_user.py
tkrcord/core/__init__.py
tkrcord/wss/__init__.py
tkrcord/wss/wsevent.py
tkrcord-0.2.9.dist-info/LICENSE
tkrcord-0.2.9.dist-info/METADATA
tkrcord-0.2.9.dist-info/WHEEL
tkrcord-0.2.9.dist-info/entry_points.txt
tkrcord-0.2.9.dist-info/top_level.txt
tkrcord-0.2.9.dist-info/RECORD
