Metadata-Version: 2.1
Name: tkrcord
Version: 0.2.9
Summary: Custom Discord API Wrapper
Home-page: https://github.com/toolkitr/tkrcord
Author: tlkr.
Author-email: "tlkr." <toolkitr.email@gmail.com>
License: The MIT License (MIT)
Project-URL: Homepage, https://github.com/toolkitr/tkrcord
Project-URL: Discussions, https://github.com/toolkitr/tkrcord/discussions
Project-URL: PullRequest, https://github.com/toolkitr/tkrcord/pulls
Project-URL: Issues, https://github.com/toolkitr/tkrcord/issues
Keywords: tkrdiscord,discordtool,tkrcord,discordtkr,discord-tkr,discord-py-tkr,discord-py-tkrcord
Classifier: License :: OSI Approved :: MIT License
Classifier: Development Status :: 1 - Planning
Classifier: Intended Audience :: Developers
Classifier: License :: OSI Approved :: MIT License
Classifier: Programming Language :: Python
Classifier: Programming Language :: Python :: 3.10
Classifier: Programming Language :: Python :: 3.11
Classifier: Topic :: Internet
Classifier: Topic :: Software Development :: Libraries
Classifier: Topic :: Software Development :: Libraries :: Python Modules
Classifier: Topic :: Utilities
Classifier: Typing :: Typed
Requires-Python: >=3.10.0,<3.12
License-File: LICENSE
Requires-Dist: aiohttp >=3.7.4
Requires-Dist: asyncio >=3.4.3
Requires-Dist: async-timeout >=3.0.1
Requires-Dist: requests >=2.26.0
Requires-Dist: datetime >=4.3.1
